phenom/__info__.py
phenom/__init__.py
phenom/__warnings__.py
phenom/_version.py
phenom/gaussian.py
phenom/io.py
phenom/mesh.py
phenom/source.py
phenom/spectrum.py
phenom/stats.py
phenom/utils.py
phenom/wavefront_tools.py
phenom/wpg.py
phenom/tests/__init__.py
phenom/tests/conftest.py
phenom/tests/test_examples.py
phenom_xfel-0.1.1.dist-info/AUTHORS.rst
phenom_xfel-0.1.1.dist-info/LICENSE
phenom_xfel-0.1.1.dist-info/METADATA
phenom_xfel-0.1.1.dist-info/WHEEL
phenom_xfel-0.1.1.dist-info/top_level.txt
phenom_xfel-0.1.1.dist-info/RECORD
