Metadata-Version: 2.1
Name: phenom_xfel
Version: 0.1.1
Summary: A phenomenological model of X-ray Free Electron Laser (XFEL) radiation and radiation statistics.
Home-page: https://github.com/twguest/phenom
Author: Trey Guest
Author-email: trey.guest@xfel.eu
License: BSD (3-clause)
Classifier: Development Status :: 2 - Pre-Alpha
Classifier: Natural Language :: English
Classifier: Programming Language :: Python :: 3
Requires-Python: >=3.8
License-File: LICENSE
License-File: AUTHORS.rst
Requires-Dist: matplotlib >=3.7.1
Requires-Dist: numpy >=1.21
Requires-Dist: scipy >=1.10.1
Requires-Dist: tables
Requires-Dist: h5py
Requires-Dist: pytest
